boip/__init__.py
boip/__main__.py
boip/app.py
boip/cli.py
boip/operation.py
boip/preset/maya-qt-mvc/boip.yaml
boip/preset/maya-qt-mvc/template/__init__.py
boip/preset/maya-qt-mvc/template/controller.py
boip/preset/maya-qt-mvc/template/model.py
boip/preset/maya-qt-mvc/template/view.py
boip/preset/maya-qt-mvc/template/gui/__init__.py
boip/preset/maya-qt-mvc/template/gui/sample_gui.py
boip/preset/maya-qt-mvc/template/gui/sample_gui.ui
Boip-0.0.3.dist-info/LICENSE
Boip-0.0.3.dist-info/METADATA
Boip-0.0.3.dist-info/WHEEL
Boip-0.0.3.dist-info/entry_points.txt
Boip-0.0.3.dist-info/top_level.txt
Boip-0.0.3.dist-info/RECORD
