Metadata-Version: 2.1
Name: Boip
Version: 0.0.3
Summary: A tool for creating Boiler Plates.
Home-page: https://github.com/InTack2/boip
Author: Tack2
Author-email: takumi236@gmail.com
License: MIT
Project-URL: Source, https://github.com/InTack2/boip
Project-URL: Documentation, https://intack2.github.io/til-note/Module/boip/
Project-URL: Tracker, https://github.com/InTack2/boip/issues
Keywords: PyInquirer,Inquirer,Maya
Platform: UNKNOWN
Classifier: Development Status :: 1 - Planning
Classifier: Environment :: Console
Classifier: Intended Audience :: Developers
Classifier: License :: OSI Approved :: MIT License
Classifier: Programming Language :: Python :: 2
Classifier: Programming Language :: Python :: 2.7
Classifier: Programming Language :: Python :: 3
Classifier: Programming Language :: Python :: 3.5
Classifier: Programming Language :: Python :: 3.6
Classifier: Programming Language :: Python :: 3.7
Classifier: Programming Language :: Python :: 3.8
Classifier: Operating System :: Microsoft :: Windows :: Windows 10
Classifier: Natural Language :: Japanese
Requires-Python: !=3.0.*,!=3.1.*,!=3.2.*,!=3.3.*,!=3.4.*,>=2.7
Requires-Dist: pyyaml (>=5.3.1)
Requires-Dist: PyInquirer (>=1.0.3)
